auto_caption/__init__.py
auto_caption/__main__.py
auto_caption-0.0.6.data/scripts/auto-caption
tests/__init__.py
auto_caption-0.0.6.dist-info/LICENSE
auto_caption-0.0.6.dist-info/METADATA
auto_caption-0.0.6.dist-info/WHEEL
auto_caption-0.0.6.dist-info/top_level.txt
auto_caption-0.0.6.dist-info/RECORD
